{
    "version": "0.0.1",
    "architecture": {
        "32bit": {
            "url": "http://github.com/thomaspoignant/api-scenario/releases/v0.0.1/api-scenario_0.0.1_Windows_i386.tar.gz",
            "bin": [
                "api-scenario.exe"
            ],
            "hash": "869cbc09c39fad6c889b7cecc5de07f0bb830fffc0aa4cf5f5dd1269e0adc230"
        },
        "64bit": {
            "url": "http://github.com/thomaspoignant/api-scenario/releases/v0.0.1/api-scenario_0.0.1_Windows_x86_64.tar.gz",
            "bin": [
                "api-scenario.exe"
            ],
            "hash": "7875c8072d0fba0b9fe6a19dbb976ac68453153a5dc8974c04c1f3f90c102952"
        }
    },
    "homepage": "https://github.com/thomaspoignant/api-scenario#api-scenario",
    "license": "Unlicence",
    "description": "Scenario API testing from the command line."
}